internetarchive_youtube/__init__.py
internetarchive_youtube/archive_youtube.py
internetarchive_youtube/cli.py
internetarchive_youtube/create_collection.py
internetarchive_youtube/jsonbin_manager.py
internetarchive_youtube-0.3.7.dist-info/LICENSE
internetarchive_youtube-0.3.7.dist-info/METADATA
internetarchive_youtube-0.3.7.dist-info/WHEEL
internetarchive_youtube-0.3.7.dist-info/entry_points.txt
internetarchive_youtube-0.3.7.dist-info/RECORD
