Metadata-Version: 2.1
Name: internetarchive-youtube
Version: 0.3.7
Summary: Archives YouTube channels by automatically uploading their videos to archive.org
License: MIT
Author: Mohammad Alyetama
Author-email: malyetama@pm.me
Requires-Python: >=3.7,<4.0
Classifier: License :: OSI Approved :: MIT License
Classifier: Programming Language :: Python :: 3
Classifier: Programming Language :: Python :: 3.7
Classifier: Programming Language :: Python :: 3.8
Classifier: Programming Language :: Python :: 3.9
Classifier: Programming Language :: Python :: 3.10
Classifier: Programming Language :: Python :: 3.11
Classifier: Programming Language :: Python :: 3.12
Requires-Dist: internetarchive (>=3.0.0)
Requires-Dist: loguru (>=0.6.0)
Requires-Dist: pymongo[srv] (>=4.0.2)
Requires-Dist: python-dotenv (>=0.20)
Requires-Dist: requests (>=2.27)
Requires-Dist: tqdm (>=4.60.0)
Requires-Dist: yt-dlp (>=2022.5.18)
